LICENSE.md
MANIFEST.in
README.md
setup.py
hass_frontend/02dc6c9b7c840ed6bff4.chunk.js
hass_frontend/02dc6c9b7c840ed6bff4.chunk.js.gz
hass_frontend/02dc6c9b7c840ed6bff4.chunk.js.map
hass_frontend/0d2180ac9aeb7a6caca5.chunk.js
hass_frontend/0d2180ac9aeb7a6caca5.chunk.js.gz
hass_frontend/0d2180ac9aeb7a6caca5.chunk.js.map
hass_frontend/1815cc03c728e6f492e1.chunk.js
hass_frontend/1815cc03c728e6f492e1.chunk.js.gz
hass_frontend/1815cc03c728e6f492e1.chunk.js.map
hass_frontend/1e756fb88e05b233692f.chunk.js
hass_frontend/1e756fb88e05b233692f.chunk.js.gz
hass_frontend/1e756fb88e05b233692f.chunk.js.map
hass_frontend/22f5a2cd72b9f140b78b.chunk.js
hass_frontend/22f5a2cd72b9f140b78b.chunk.js.map
hass_frontend/23c139d3e603cb500514.chunk.js
hass_frontend/23c139d3e603cb500514.chunk.js.gz
hass_frontend/23c139d3e603cb500514.chunk.js.map
hass_frontend/2c5789b57867a30c34ad.chunk.js
hass_frontend/2c5789b57867a30c34ad.chunk.js.LICENSE
hass_frontend/2c5789b57867a30c34ad.chunk.js.gz
hass_frontend/2c5789b57867a30c34ad.chunk.js.map
hass_frontend/495a01ffb0b2bf2f1512.chunk.js
hass_frontend/495a01ffb0b2bf2f1512.chunk.js.gz
hass_frontend/495a01ffb0b2bf2f1512.chunk.js.map
hass_frontend/4c17d2b4c1d46539e67a.chunk.js
hass_frontend/4c17d2b4c1d46539e67a.chunk.js.LICENSE
hass_frontend/4c17d2b4c1d46539e67a.chunk.js.gz
hass_frontend/4c17d2b4c1d46539e67a.chunk.js.map
hass_frontend/4c22bc737277ec20f50f.chunk.js
hass_frontend/4c22bc737277ec20f50f.chunk.js.LICENSE
hass_frontend/4c22bc737277ec20f50f.chunk.js.gz
hass_frontend/4c22bc737277ec20f50f.chunk.js.map
hass_frontend/51040417db0f0508e15f.chunk.js
hass_frontend/51040417db0f0508e15f.chunk.js.LICENSE
hass_frontend/51040417db0f0508e15f.chunk.js.gz
hass_frontend/51040417db0f0508e15f.chunk.js.map
hass_frontend/5e9d170d6c2077c609ef.chunk.js
hass_frontend/5e9d170d6c2077c609ef.chunk.js.gz
hass_frontend/5e9d170d6c2077c609ef.chunk.js.map
hass_frontend/6487caca296d75afa810.chunk.js
hass_frontend/6487caca296d75afa810.chunk.js.gz
trixie_frontend.egg-info/PKG-INFO
trixie_frontend.egg-info/SOURCES.txt
trixie_frontend.egg-info/dependency_links.txt
trixie_frontend.egg-info/not-zip-safe
trixie_frontend.egg-info/requires.txt
trixie_frontend.egg-info/top_level.txt