Metadata-Version: 1.0
Name: trixie-frontend
Version: 20180628.1
Summary: The Trixie frontend
Home-page: https://github.com/charbelsarkis/trixie-frontend
Author: Trixie Home Assistant Authors
Author-email: hello@trixie.io
License: Apache License 2.0
Platform: UNKNOWN
